cryptounifier/BaseApi.py
cryptounifier/MerchantApi.py
cryptounifier/WalletApi.py
cryptounifier/WalletTokenApi.py
cryptounifier/__init__.py
cryptounifier-1.0.4.dist-info/LICENSE.md
cryptounifier-1.0.4.dist-info/METADATA
cryptounifier-1.0.4.dist-info/WHEEL
cryptounifier-1.0.4.dist-info/top_level.txt
cryptounifier-1.0.4.dist-info/RECORD
